lazypsf/__init__.py
lazypsf/fkdat.py
lazypsf/r_psf.py
lazypsf/config/default.conv
lazypsf/config/default.nnw
lazypsf/config/default.param
lazypsf/config/default.sex
lazypsf/config/psfex.conf
lazypsf/config/r_psf.conv
lazypsf/config/r_psf.param
lazypsf/config/r_psf.sex
lazypsf-4.3.1.dist-info/LICENSE.txt
lazypsf-4.3.1.dist-info/METADATA
lazypsf-4.3.1.dist-info/WHEEL
lazypsf-4.3.1.dist-info/top_level.txt
lazypsf-4.3.1.dist-info/RECORD
