Metadata-Version: 2.1
Name: lazypsf
Version: 4.3.1
Summary: A code for modelling PSFs and injecting fake sources with given flux distributions. Simulating Astro data
Home-page: https://github.com/ryanc123/LazyPSF
Author: Ry Cutter
Author-email: R.Cutter@warwick.ac.uk
License: GNU
Platform: UNKNOWN
